stocks_toolkit/API_wrapper.py
stocks_toolkit/__init__.py
stocks_toolkit/candle_analysis.py
stocks_toolkit/exceptions.py
stocks_toolkit/helper.py
stocks_toolkit/retrieval_layer.py
stocks_toolkit/stocks_toolkit.py
stocks_toolkit/stocksymbols.csv
stocks_toolkit_india-0.1.49.dist-info/LICENSE
stocks_toolkit_india-0.1.49.dist-info/METADATA
stocks_toolkit_india-0.1.49.dist-info/WHEEL
stocks_toolkit_india-0.1.49.dist-info/top_level.txt
stocks_toolkit_india-0.1.49.dist-info/RECORD
