Metadata-Version: 2.1
Name: stocks-toolkit-india
Version: 0.1.49
Summary: Toolkit for performing analysis on indian stock market
Home-page: https://github.com/Colo55us/stocks_toolkit_india
Author: Mohit Pratap Singh
Author-email: mohit.planed@gmail.com
License: MIT
Platform: UNKNOWN
Classifier: License :: OSI Approved :: MIT License
Classifier: Development Status :: 5 - Production/Stable
Classifier: Programming Language :: Python :: 3
Classifier: Programming Language :: Python :: 3.7
Requires-Dist: numpy
Requires-Dist: pandas
Requires-Dist: TA-lib
Requires-Dist: requests
Requires-Dist: datetime
Requires-Dist: bs4
